{
    "title": "Proposition Document Standards",
    "prop": "1-7",
    "data": "Sept. 28th, Y7",
    "articleCount": "1",
    "reason": "standardize proposition documents",
    "proposedBy": ["thesandmannn"],
    "ministryOf": null,
    "billOrResolution": "bill",
    "approvedStatus": "Awaiting approval from the Council.",
    "resources": [
        {
            "identifier": "1-7-R1",
            "docLink": "https://docs.google.com/document/d/1aFao0XOHGyYnJ2llA8WA7igzXHqnW1YzT8LdQb12SG8"
        },
        {
            "identifier": "1-7-R1-1",
            "docLink": "https://docs.google.com/document/d/1dUgx2UPksDDzLM42AFhS256vK6Ya2RmnK_KK6pkxwYM"
        }
    ],
    "votes": {
        "yes": [],
        "no": []   
    },
    "docLink": "https://docs.google.com/document/d/1d__TcBSAX0m9JDn4Sw9afjnUoc7mYlXxwhdKkfv2SuU"
}